shareloc_utils/VERSION
shareloc_utils/__init__.py
shareloc_utils/batch_download.py
shareloc_utils/formats.py
shareloc_utils/smlm_file.py
shareloc_utils-0.1.10.dist-info/LICENSE
shareloc_utils-0.1.10.dist-info/METADATA
shareloc_utils-0.1.10.dist-info/WHEEL
shareloc_utils-0.1.10.dist-info/top_level.txt
shareloc_utils-0.1.10.dist-info/RECORD
