Metadata-Version: 2.1
Name: shareloc-utils
Version: 0.1.10
Summary: Utility tools for ShareLoc.XYZ
Home-page: https://github.com/imodpasteur/shareloc_utils
Author: imod-pasteur
Author-email: shareloc@pasteur.fr
License: MIT
Platform: UNKNOWN
Classifier: Development Status :: 3 - Alpha
Classifier: Environment :: Web Environment
Classifier: Intended Audience :: Developers
Classifier: License :: OSI Approved :: MIT License
Classifier: Operating System :: OS Independent
Classifier: Programming Language :: Python
Classifier: Programming Language :: Python :: 3.6
Classifier: Programming Language :: Python :: 3.7
Classifier: Programming Language :: Python :: 3.8
Classifier: Programming Language :: Python :: 3.9
Classifier: Topic :: Internet
Requires-Python: >=3.6
License-File: LICENSE
Requires-Dist: numpy
Requires-Dist: pyyaml
Requires-Dist: pillow
Requires-Dist: tqdm
Provides-Extra: potree
Requires-Dist: pypotree ; extra == 'potree'
